featuretools/__init__.py
featuretools/__main__.py
featuretools/config_init.py
featuretools/exceptions.py
featuretools/version.py
featuretools/computational_backends/__init__.py
featuretools/computational_backends/api.py
featuretools/computational_backends/base_backend.py
featuretools/computational_backends/calculate_feature_matrix.py
featuretools/computational_backends/feature_tree.py
featuretools/computational_backends/pandas_backend.py
featuretools/computational_backends/utils.py
featuretools/demo/__init__.py
featuretools/demo/api.py
featuretools/demo/flight.py
featuretools/demo/mock_customer.py
featuretools/demo/retail.py
featuretools/entityset/__init__.py
featuretools/entityset/api.py
featuretools/entityset/deserialize.py
featuretools/entityset/entity.py
featuretools/entityset/entityset.py
featuretools/entityset/relationship.py
featuretools/entityset/serialize.py
featuretools/entityset/timedelta.py
featuretools/feature_base/__init__.py
featuretools/feature_base/api.py
featuretools/feature_base/feature_base.py
featuretools/feature_base/features_deserializer.py
featuretools/feature_base/features_serializer.py
featuretools/primitives/__init__.py
featuretools/primitives/api.py
featuretools/primitives/utils.py
featuretools/primitives/base/__init__.py
featuretools/primitives/base/aggregation_primitive_base.py
featuretools/primitives/base/api.py
featuretools/primitives/base/primitive_base.py
featuretools/primitives/base/transform_primitive_base.py
featuretools/primitives/base/utils.py
featuretools/primitives/data/featuretools_unit_test_example.csv
featuretools/primitives/standard/__init__.py
featuretools/primitives/standard/aggregation_primitives.py
featuretools/primitives/standard/api.py
featuretools/primitives/standard/binary_transform.py
featuretools/primitives/standard/cum_transform_feature.py
featuretools/primitives/standard/transform_primitive.py
featuretools/selection/__init__.py
featuretools/selection/api.py
featuretools/selection/selection.py
featuretools_MV-0.8.0.dist-info/LICENSE
featuretools_MV-0.8.0.dist-info/METADATA
featuretools_MV-0.8.0.dist-info/WHEEL
featuretools_MV-0.8.0.dist-info/entry_points.txt
featuretools_MV-0.8.0.dist-info/top_level.txt
featuretools_MV-0.8.0.dist-info/RECORD
