Metadata-Version: 2.1
Name: featuretools-MV
Version: 0.8.0
Summary: a framework for automated feature engineering
Home-page: http://featuretools.com
Author: Feature Labs, Inc.
Author-email: support@featurelabs.com
License: BSD 3-clause
Keywords: feature engineering data science machine learning
Platform: UNKNOWN
Classifier: Development Status :: 3 - Alpha
Classifier: Intended Audience :: Developers
Classifier: Programming Language :: Python :: 2.7
Classifier: Programming Language :: Python :: 3
Classifier: Programming Language :: Python :: 3.5
Classifier: Programming Language :: Python :: 3.6
Classifier: Programming Language :: Python :: 3.7
Requires-Python: >=2.7, <4
Requires-Dist: numpy (>=1.13.3)
Requires-Dist: pandas (>=0.22.0)
Requires-Dist: tqdm (>=4.19.2)
Requires-Dist: toolz (>=0.8.2)
Requires-Dist: pyyaml (>=3.12)
Requires-Dist: cloudpickle (>=0.4.0)
Requires-Dist: future (>=0.16.0)
Requires-Dist: dask (>=1.1.0)
Requires-Dist: distributed (>=1.24.2)
Requires-Dist: psutil (>=5.4.8)
Requires-Dist: click (>=6.7.0)
Requires-Dist: scikit-learn (<0.21,>=0.20.0) ; python_version < "3"
Requires-Dist: funcsigs (>=1.0.2) ; python_version < "3"
Requires-Dist: scikit-learn (>=0.20.0) ; python_version >= "3"
